{
  "Profiles": [
    {
      "ASCII Anti Aliased": true,
      "ASCII Ligatures": false,
      "AWDS Pane Directory": "",
      "AWDS Pane Option": "Recycle",
      "AWDS Tab Directory": "",
      "AWDS Tab Option": "Recycle",
      "AWDS Window Directory": "~/Documents/",
      "AWDS Window Option": "Yes",
      "Allow Title Setting": false,
      "Ambiguous Double Width": false,
      "Ansi 0 Color": {
        "Blue Component": 0.15294117647058825,
        "Color Space": "sRGB",
        "Green Component": 0.08627450980392157,
        "Red Component": 0.00392156862745098
      },
      "Ansi 0 Color (Dark)": {
        "Blue Component": 0,
        "Green Component": 0,
        "Red Component": 0
      },
      "Ansi 0 Color (Light)": {
        "Blue Component": 0.15294117647058825,
        "Color Space": "sRGB",
        "Green Component": 0.08627450980392157,
        "Red Component": 0.00392156862745098
      },
      "Ansi 1 Color": {
        "Blue Component": 0.24313725490196078,
        "Color Space": "sRGB",
        "Green Component": 0.25882352941176473,
        "Red Component": 0.8274509803921568
      },
      "Ansi 1 Color (Dark)": {
        "Blue Component": 0,
        "Green Component": 0,
        "Red Component": 0.6
      },
      "Ansi 1 Color (Light)": {
        "Blue Component": 0.24313725490196078,
        "Color Space": "sRGB",
        "Green Component": 0.25882352941176473,
        "Red Component": 0.8274509803921568
      },
      "Ansi 10 Color": {
        "Blue Component": 0.7725490196078432,
        "Color Space": "sRGB",
        "Green Component": 0.8156862745098039,
        "Red Component": 0.28627450980392155
      },
      "Ansi 10 Color (Dark)": {
        "Blue Component": 0,
        "Green Component": 0.8509803921568627,
        "Red Component": 0
      },
      "Ansi 10 Color (Light)": {
        "Blue Component": 0.7725490196078432,
        "Color Space": "sRGB",
        "Green Component": 0.8156862745098039,
        "Red Component": 0.28627450980392155
      },
      "Ansi 11 Color": {
        "Blue Component": 0.4196078431372549,
        "Color Space": "sRGB",
        "Green Component": 0.7607843137254902,
        "Red Component": 0.8549019607843137
      },
      "Ansi 11 Color (Dark)": {
        "Blue Component": 0,
        "Green Component": 0.8980392156862745,
        "Red Component": 0.8980392156862745
      },
      "Ansi 11 Color (Light)": {
        "Blue Component": 0.4196078431372549,
        "Color Space": "sRGB",
        "Green Component": 0.7607843137254902,
        "Red Component": 0.8549019607843137
      },
      "Ansi 12 Color": {
        "Blue Component": 0.8941176470588236,
        "Color Space": "sRGB",
        "Green Component": 0.6549019607843137,
        "Red Component": 0.3607843137254902
      },
      "Ansi 12 Color (Dark)": {
        "Blue Component": 1,
        "Green Component": 0,
        "Red Component": 0
      },
      "Ansi 12 Color (Light)": {
        "Blue Component": 0.8941176470588236,
        "Color Space": "sRGB",
        "Green Component": 0.6549019607843137,
        "Red Component": 0.3607843137254902
      },
      "Ansi 13 Color": {
        "Blue Component": 0.596078431372549,
        "Color Space": "sRGB",
        "Green Component": 0.4392156862745098,
        "Red Component": 0.4117647058823529
      },
      "Ansi 13 Color (Dark)": {
        "Blue Component": 0.8980392156862745,
        "Green Component": 0,
        "Red Component": 0.8980392156862745
      },
      "Ansi 13 Color (Light)": {
        "Blue Component": 0.596078431372549,
        "Color Space": "sRGB",
        "Green Component": 0.4392156862745098,
        "Red Component": 0.4117647058823529
      },
      "Ansi 14 Color": {
        "Blue Component": 0.5647058823529412,
        "Color Space": "sRGB",
        "Green Component": 0.788235294117647,
        "Red Component": 0
      },
      "Ansi 14 Color (Dark)": {
        "Blue Component": 0.8980392156862745,
        "Green Component": 0.8980392156862745,
        "Red Component": 0
      },
      "Ansi 14 Color (Light)": {
        "Blue Component": 0.5647058823529412,
        "Color Space": "sRGB",
        "Green Component": 0.788235294117647,
        "Red Component": 0
      },
      "Ansi 15 Color": {
        "Blue Component": 0.6941176470588235,
        "Color Space": "sRGB",
        "Green Component": 0.6235294117647059,
        "Red Component": 0.596078431372549
      },
      "Ansi 15 Color (Dark)": {
        "Blue Component": 0.8980392156862745,
        "Green Component": 0.8980392156862745,
        "Red Component": 0.8980392156862745
      },
      "Ansi 15 Color (Light)": {
        "Blue Component": 0.6941176470588235,
        "Color Space": "sRGB",
        "Green Component": 0.6235294117647059,
        "Red Component": 0.596078431372549
      },
      "Ansi 2 Color": {
        "Blue Component": 0.596078431372549,
        "Color Space": "sRGB",
        "Green Component": 0.6352941176470588,
        "Red Component": 0.16470588235294117
      },
      "Ansi 2 Color (Dark)": {
        "Blue Component": 0,
        "Green Component": 0.6509803921568628,
        "Red Component": 0
      },
      "Ansi 2 Color (Light)": {
        "Blue Component": 0.596078431372549,
        "Color Space": "sRGB",
        "Green Component": 0.6352941176470588,
        "Red Component": 0.16470588235294117
      },
      "Ansi 3 Color": {
        "Blue Component": 0.00392156862745098,
        "Color Space": "sRGB",
        "Green Component": 0.6666666666666666,
        "Red Component": 0.8549019607843137
      },
      "Ansi 3 Color (Dark)": {
        "Blue Component": 0,
        "Green Component": 0.6,
        "Red Component": 0.6
      },
      "Ansi 3 Color (Light)": {
        "Blue Component": 0.00392156862745098,
        "Color Space": "sRGB",
        "Green Component": 0.6666666666666666,
        "Red Component": 0.8549019607843137
      },
      "Ansi 4 Color": {
        "Blue Component": 0.8392156862745098,
        "Color Space": "sRGB",
        "Green Component": 0.4627450980392157,
        "Red Component": 0.2823529411764706
      },
      "Ansi 4 Color (Dark)": {
        "Blue Component": 0.6980392156862745,
        "Green Component": 0,
        "Red Component": 0
      },
      "Ansi 4 Color (Light)": {
        "Blue Component": 0.8392156862745098,
        "Color Space": "sRGB",
        "Green Component": 0.4627450980392157,
        "Red Component": 0.2823529411764706
      },
      "Ansi 5 Color": {
        "Blue Component": 0.3254901960784314,
        "Color Space": "sRGB",
        "Green Component": 0.24705882352941178,
        "Red Component": 0.25098039215686274
      },
      "Ansi 5 Color (Dark)": {
        "Blue Component": 0.6980392156862745,
        "Green Component": 0,
        "Red Component": 0.6980392156862745
      },
      "Ansi 5 Color (Light)": {
        "Blue Component": 0.3254901960784314,
        "Color Space": "sRGB",
        "Green Component": 0.24705882352941178,
        "Red Component": 0.25098039215686274
      },
      "Ansi 6 Color": {
        "Blue Component": 0.41568627450980394,
        "Color Space": "sRGB",
        "Green Component": 0.5686274509803921,
        "Red Component": 0.03137254901960784
      },
      "Ansi 6 Color (Dark)": {
        "Blue Component": 0.6980392156862745,
        "Green Component": 0.6509803921568628,
        "Red Component": 0
      },
      "Ansi 6 Color (Light)": {
        "Blue Component": 0.41568627450980394,
        "Color Space": "sRGB",
        "Green Component": 0.5686274509803921,
        "Red Component": 0.03137254901960784
      },
      "Ansi 7 Color": {
        "Blue Component": 0.5058823529411764,
        "Color Space": "sRGB",
        "Green Component": 0.5058823529411764,
        "Red Component": 0.47843137254901963
      },
      "Ansi 7 Color (Dark)": {
        "Blue Component": 0.7490196078431373,
        "Green Component": 0.7490196078431373,
        "Red Component": 0.7490196078431373
      },
      "Ansi 7 Color (Light)": {
        "Blue Component": 0.5058823529411764,
        "Color Space": "sRGB",
        "Green Component": 0.5058823529411764,
        "Red Component": 0.47843137254901963
      },
      "Ansi 8 Color": {
        "Blue Component": 0.5058823529411764,
        "Color Space": "sRGB",
        "Green Component": 0.5058823529411764,
        "Red Component": 0.47843137254901963
      },
      "Ansi 8 Color (Dark)": {
        "Blue Component": 0.4,
        "Green Component": 0.4,
        "Red Component": 0.4
      },
      "Ansi 8 Color (Light)": {
        "Blue Component": 0.5058823529411764,
        "Color Space": "sRGB",
        "Green Component": 0.5058823529411764,
        "Red Component": 0.47843137254901963
      },
      "Ansi 9 Color": {
        "Blue Component": 0.43137254901960786,
        "Color Space": "sRGB",
        "Green Component": 0.43137254901960786,
        "Red Component": 0.9686274509803922
      },
      "Ansi 9 Color (Dark)": {
        "Blue Component": 0,
        "Green Component": 0,
        "Red Component": 0.8980392156862745
      },
      "Ansi 9 Color (Light)": {
        "Blue Component": 0.43137254901960786,
        "Color Space": "sRGB",
        "Green Component": 0.43137254901960786,
        "Red Component": 0.9686274509803922
      },
      "Application Keypad Allowed": true,
      "BM Growl": true,
      "Background Color": {
        "Blue Component": 1,
        "Color Space": "sRGB",
        "Green Component": 1,
        "Red Component": 1
      },
      "Background Color (Dark)": {
        "Blue Component": 0,
        "Green Component": 0,
        "Red Component": 0
      },
      "Background Color (Light)": {
        "Blue Component": 1,
        "Color Space": "sRGB",
        "Green Component": 1,
        "Red Component": 1
      },
      "Background Image Location": "",
      "Badge Color": {
        "Alpha Component": 0.5,
        "Blue Component": 0.13960540294647217,
        "Color Space": "P3",
        "Green Component": 0.25479039549827576,
        "Red Component": 0.9292940497398376
      },
      "Badge Color (Dark)": {
        "Alpha Component": 0.5,
        "Blue Component": 0.13960540294647217,
        "Color Space": "P3",
        "Green Component": 0.25479039549827576,
        "Red Component": 0.9292940497398376
      },
      "Badge Color (Light)": {
        "Alpha Component": 0.5,
        "Blue Component": 0.13960540294647217,
        "Color Space": "P3",
        "Green Component": 0.25479039549827576,
        "Red Component": 0.9292940497398376
      },
      "Badge Font": "MonaspaceKrypton-Bold",
      "Badge Max Height": 0.3,
      "Badge Max Width": 0.5,
      "Badge Right Margin": 30,
      "Badge Text": "",
      "Badge Top Margin": 0,
      "Blink Allowed": true,
      "Blinking Cursor": false,
      "Blur": true,
      "Blur Radius": 8.3475194321066,
      "Bold Color": {
        "Blue Component": 0.3254901960784314,
        "Color Space": "sRGB",
        "Green Component": 0.24705882352941178,
        "Red Component": 0.25098039215686274
      },
      "Bold Color (Dark)": {
        "Blue Component": 0,
        "Green Component": 1,
        "Red Component": 0
      },
      "Bold Color (Light)": {
        "Blue Component": 0.3254901960784314,
        "Color Space": "sRGB",
        "Green Component": 0.24705882352941178,
        "Red Component": 0.25098039215686274
      },
      "Bound Hosts": [
        "ianchamberlain",
        "ichamberlain",
        "ichamberlain@ian-dev",
        "ichamberlain@ian-dev.openstacklocal",
        "ichamberlain@Ians-Macbook-Pro.local",
        "ichamberlain@ichamberlain-mbp"
      ],
      "Brighten Bold Text (Dark)": false,
      "Brighten Bold Text (Light)": false,
      "Character Encoding": 4,
      "Close Sessions On End": true,
      "Columns": 80,
      "Command": "/usr/local/bin/fish -il",
      "Cursor Boost (Dark)": 0,
      "Cursor Boost (Light)": 0,
      "Cursor Color": {
        "Blue Component": 0.3254901960784314,
        "Color Space": "sRGB",
        "Green Component": 0.24705882352941178,
        "Red Component": 0.25098039215686274
      },
      "Cursor Color (Dark)": {
        "Blue Component": 0.09411764705882353,
        "Green Component": 1,
        "Red Component": 0.13725490196078433
      },
      "Cursor Color (Light)": {
        "Blue Component": 0.3254901960784314,
        "Color Space": "sRGB",
        "Green Component": 0.24705882352941178,
        "Red Component": 0.25098039215686274
      },
      "Cursor Guide Color": {
        "Alpha Component": 0.25,
        "Blue Component": 0.9912572503089905,
        "Color Space": "P3",
        "Green Component": 0.9204778671264648,
        "Red Component": 0.7486259937286377
      },
      "Cursor Guide Color (Dark)": {
        "Alpha Component": 0.25,
        "Blue Component": 0.9912572503089905,
        "Color Space": "P3",
        "Green Component": 0.9204778671264648,
        "Red Component": 0.7486259937286377
      },
      "Cursor Guide Color (Light)": {
        "Alpha Component": 0.25,
        "Blue Component": 0.9912572503089905,
        "Color Space": "P3",
        "Green Component": 0.9204778671264648,
        "Red Component": 0.7486259937286377
      },
      "Cursor Text Color": {
        "Blue Component": 0.984313725490196,
        "Color Space": "sRGB",
        "Green Component": 0.984313725490196,
        "Red Component": 0.984313725490196
      },
      "Cursor Text Color (Dark)": {
        "Blue Component": 0.0940093994140625,
        "Green Component": 0,
        "Red Component": 1
      },
      "Cursor Text Color (Light)": {
        "Blue Component": 0.984313725490196,
        "Color Space": "sRGB",
        "Green Component": 0.984313725490196,
        "Red Component": 0.984313725490196
      },
      "Custom Command": "No",
      "Custom Directory": "Advanced",
      "Default Bookmark": "No",
      "Description": "Default",
      "Disable Window Resizing": false,
      "Draw Powerline Glyphs": true,
      "Dynamic Profile Filename": "/Users/ianchamberlain/.config/iterm2/profiles/Default.json",
      "Faint Text Alpha (Dark)": 0.5,
      "Faint Text Alpha (Light)": 0.5,
      "Flashing Bell": true,
      "Foreground Color": {
        "Blue Component": 0.3254901960784314,
        "Color Space": "sRGB",
        "Green Component": 0.24705882352941178,
        "Red Component": 0.25098039215686274
      },
      "Foreground Color (Dark)": {
        "Blue Component": 0,
        "Green Component": 1,
        "Red Component": 0
      },
      "Foreground Color (Light)": {
        "Blue Component": 0.3254901960784314,
        "Color Space": "sRGB",
        "Green Component": 0.24705882352941178,
        "Red Component": 0.25098039215686274
      },
      "Guid": "21922352-0CDF-42DB-B31E-C78ABCAAEA80",
      "Horizontal Spacing": 1,
      "Idle Code": 0,
      "Jobs to Ignore": [],
      "Keyboard Map": {
        "0x20-0x80000": {
          "Action": 13,
          "Text": ""
        },
        "0x2a-0x200000": {
          "Action": 12,
          "Text": "*"
        },
        "0x2b-0x200000": {
          "Action": 12,
          "Text": "+"
        },
        "0x2d-0x200000": {
          "Action": 12,
          "Text": "-"
        },
        "0x2d-0x40000": {
          "Action": 11,
          "Text": "0x1f"
        },
        "0x2e-0x200000": {
          "Action": 12,
          "Text": "."
        },
        "0x2f-0x200000": {
          "Action": 12,
          "Text": "/"
        },
        "0x3-0x200000": {
          "Action": 11,
          "Text": "0x0D"
        },
        "0x30-0x200000": {
          "Action": 12,
          "Text": "0"
        },
        "0x31-0x200000": {
          "Action": 12,
          "Text": "1"
        },
        "0x32-0x200000": {
          "Action": 12,
          "Text": "2"
        },
        "0x33-0x200000": {
          "Action": 12,
          "Text": "3"
        },
        "0x34-0x200000": {
          "Action": 12,
          "Text": "4"
        },
        "0x35-0x200000": {
          "Action": 12,
          "Text": "5"
        },
        "0x36-0x200000": {
          "Action": 12,
          "Text": "6"
        },
        "0x37-0x200000": {
          "Action": 12,
          "Text": "7"
        },
        "0x38-0x200000": {
          "Action": 12,
          "Text": "8"
        },
        "0x39-0x200000": {
          "Action": 12,
          "Text": "9"
        },
        "0x7f-0x100000": {
          "Action": 11,
          "Text": "0x15"
        },
        "0x7f-0x80000": {
          "Action": 11,
          "Text": "0x1B 0x08"
        },
        "0xd-0x80000-0x24": {
          "Action": 10,
          "Label": "",
          "Text": "\n",
          "Version": 1
        },
        "0xf702-0x280000": {
          "Action": 10,
          "Text": "b"
        },
        "0xf702-0x300000": {
          "Action": 10,
          "Text": "[H"
        },
        "0xf703-0x280000": {
          "Action": 10,
          "Text": "f"
        },
        "0xf703-0x300000": {
          "Action": 10,
          "Text": "[F"
        },
        "0xf728-0x100000-0x75": {
          "Action": 11,
          "Apply Mode": 0,
          "Escaping": 2,
          "Text": "0B",
          "Version": 2
        },
        "0xf728-0x80000": {
          "Action": 10,
          "Text": "d"
        },
        "0xf739-0x0": {
          "Action": 13,
          "Text": ""
        }
      },
      "Link Color": {
        "Alpha Component": 1,
        "Blue Component": 0.709324061870575,
        "Color Space": "P3",
        "Green Component": 0.35333043336868286,
        "Red Component": 0.1451396644115448
      },
      "Link Color (Dark)": {
        "Alpha Component": 1,
        "Blue Component": 0.709324061870575,
        "Color Space": "P3",
        "Green Component": 0.35333043336868286,
        "Red Component": 0.1451396644115448
      },
      "Link Color (Light)": {
        "Alpha Component": 1,
        "Blue Component": 0.709324061870575,
        "Color Space": "P3",
        "Green Component": 0.35333043336868286,
        "Red Component": 0.1451396644115448
      },
      "Match Background Color": {
        "Alpha Component": 1,
        "Blue Component": 0,
        "Color Space": "P3",
        "Green Component": 1,
        "Red Component": 1
      },
      "Match Background Color (Dark)": {
        "Alpha Component": 1,
        "Blue Component": 0,
        "Color Space": "P3",
        "Green Component": 1,
        "Red Component": 1
      },
      "Match Background Color (Light)": {
        "Alpha Component": 1,
        "Blue Component": 0,
        "Color Space": "P3",
        "Green Component": 1,
        "Red Component": 1
      },
      "Minimum Contrast (Dark)": 0,
      "Minimum Contrast (Light)": 0,
      "Mouse Reporting": true,
      "Name": "Default",
      "Non Ascii Font": "MonaspiceArNF-Regular 12",
      "Non-ASCII Anti Aliased": true,
      "Normal Font": "MonaspaceArgon-Regular 12 {\"featureSettings\":[{\"CTFeatureSelectorIdentifier\":16,\"CTFeatureTypeIdentifier\":35},{\"CTFeatureSelectorIdentifier\":8,\"CTFeatureTypeIdentifier\":35},{\"CTFeatureSelectorIdentifier\":12,\"CTFeatureTypeIdentifier\":35},{\"CTFeatureSelectorIdentifier\":6,\"CTFeatureTypeIdentifier\":35},{\"CTFeatureSelectorIdentifier\":10,\"CTFeatureTypeIdentifier\":35},{\"CTFeatureSelectorIdentifier\":18,\"CTFeatureTypeIdentifier\":35},{\"CTFeatureSelectorIdentifier\":14,\"CTFeatureTypeIdentifier\":35}]}",
      "Only The Default BG Color Uses Transparency": false,
      "Open Toolbelt": false,
      "Option Key Sends": 0,
      "Place Prompt at First Column": false,
      "Prompt Before Closing 2": 2,
      "Right Option Key Sends": 0,
      "Rows": 25,
      "Screen": -1,
      "Scrollback Lines": 0,
      "Selected Text Color": {
        "Blue Component": 0.3254901960784314,
        "Color Space": "sRGB",
        "Green Component": 0.24705882352941178,
        "Red Component": 0.25098039215686274
      },
      "Selected Text Color (Dark)": {
        "Blue Component": 1,
        "Green Component": 1,
        "Red Component": 1
      },
      "Selected Text Color (Light)": {
        "Blue Component": 0.3254901960784314,
        "Color Space": "sRGB",
        "Green Component": 0.24705882352941178,
        "Red Component": 0.25098039215686274
      },
      "Selection Color": {
        "Blue Component": 0.95,
        "Color Space": "sRGB",
        "Green Component": 0.95,
        "Red Component": 0.95
      },
      "Selection Color (Dark)": {
        "Blue Component": 0.0196078431372549,
        "Green Component": 0.22352941176470587,
        "Red Component": 0.03137254901960784
      },
      "Selection Color (Light)": {
        "Blue Component": 0.95,
        "Color Space": "sRGB",
        "Green Component": 0.95,
        "Red Component": 0.95
      },
      "Semantic History": {
        "action": "best editor",
        "editor": "com.github.atom",
        "text": ""
      },
      "Send Code When Idle": false,
      "Send Session Ended Alert": false,
      "Session Close Undo Timeout": 0,
      "Set Local Environment Vars": true,
      "Shortcut": "",
      "Show Mark Indicators": false,
      "Show Status Bar": true,
      "Silence Bell": false,
      "Smart Cursor Color (Dark)": false,
      "Smart Cursor Color (Light)": false,
      "Space": 0,
      "Special Font Config": "{\"entries\":[{\"count\":4,\"fontName\":\"UnicodeIECsymbol\",\"start\":9211},{\"fontName\":\"Octicons\",\"start\":9829,\"count\":1},{\"fontName\":\"Octicons\",\"start\":9889,\"count\":1},{\"start\":11096,\"count\":1,\"fontName\":\"UnicodeIECsymbol\"},{\"fontName\":\"Pomicons\",\"start\":57344,\"count\":11},{\"start\":57504,\"count\":3,\"fontName\":\"PowerlineSymbols\"},{\"count\":1,\"start\":57507,\"fontName\":\"PowerlineExtraSymbols\"},{\"fontName\":\"PowerlineSymbols\",\"count\":4,\"start\":57520},{\"count\":21,\"fontName\":\"PowerlineExtraSymbols\",\"start\":57524},{\"count\":1,\"start\":57546,\"fontName\":\"PowerlineExtraSymbols\"},{\"fontName\":\"PowerlineExtraSymbols\",\"count\":8,\"start\":57548},{\"destination\":57856,\"start\":57344,\"count\":170,\"fontName\":\"font-awesome-extension\"},{\"destination\":58112,\"start\":61440,\"fontName\":\"Weather Icons Regular\",\"count\":236},{\"start\":58618,\"count\":177,\"destination\":58874,\"fontName\":\"Nerd Font File Types Regular\"},{\"start\":58880,\"count\":198,\"destination\":59136,\"fontName\":\"icomoon\"},{\"start\":60000,\"count\":396,\"fontName\":\"codicon\"},{\"count\":736,\"fontName\":\"FontAwesome\",\"start\":61440},{\"start\":62208,\"count\":48,\"fontName\":\"font-logos\"},{\"fontName\":\"Octicons\",\"count\":168,\"start\":61440,\"destination\":62464},{\"count\":1,\"destination\":62633,\"start\":62076,\"fontName\":\"Octicons\"},{\"fontName\":\"Octicons\",\"start\":61609,\"count\":86,\"destination\":62634},{\"start\":61441,\"count\":2118,\"fontName\":\"Material Design Icons\",\"destination\":62720},{\"start\":983041,\"count\":6896,\"fontName\":\"Material Design Icons Desktop\"}],\"version\":1}",
      "Status Bar Layout": {
        "advanced configuration": {
          "algorithm": 0,
          "font": "MonaspaceArgonVar-Medium 12"
        },
        "components": [
          {
            "class": "iTermStatusBarJobComponent",
            "configuration": {
              "knobs": {
                "base: compression resistance": 1,
                "base: priority": 5,
                "maxwidth": 1.7976931348623157e+308,
                "minwidth": 0,
                "shared text color": {
                  "Alpha Component": 1,
                  "Blue Component": 0.63,
                  "Color Space": "sRGB",
                  "Green Component": 0.63,
                  "Red Component": 0.9
                }
              },
              "layout advanced configuration dictionary value": {
                "algorithm": 0,
                "font": "MonaspaceArgonVar-Medium 12"
              }
            }
          },
          {
            "class": "iTermStatusBarWorkingDirectoryComponent",
            "configuration": {
              "knobs": {
                "base: compression resistance": 1,
                "base: priority": 5,
                "maxwidth": 1.7976931348623157e+308,
                "minwidth": 0,
                "path": "path",
                "shared text color": {
                  "Alpha Component": 1,
                  "Blue Component": 0.63,
                  "Color Space": "sRGB",
                  "Green Component": 0.9,
                  "Red Component": 0.846
                }
              },
              "layout advanced configuration dictionary value": {
                "algorithm": 0,
                "font": "MonaspaceArgonVar-Medium 12"
              }
            }
          },
          {
            "class": "iTermStatusBarGitComponent",
            "configuration": {
              "knobs": {
                "base: compression resistance": 1,
                "base: priority": 5,
                "iTermStatusBarGitComponentPollingIntervalKey": 2,
                "maxwidth": 1.7976931348623157e+308,
                "minwidth": 0,
                "shared text color": {
                  "Alpha Component": 1,
                  "Blue Component": 0.7380000000000001,
                  "Color Space": "sRGB",
                  "Green Component": 0.9,
                  "Red Component": 0.63
                }
              },
              "layout advanced configuration dictionary value": {
                "algorithm": 0,
                "font": "MonaspaceArgonVar-Medium 12"
              }
            }
          },
          {
            "class": "iTermStatusBarCPUUtilizationComponent",
            "configuration": {
              "knobs": {
                "base: compression resistance": 1,
                "base: priority": 5,
                "shared text color": {
                  "Alpha Component": 1,
                  "Blue Component": 0.9,
                  "Color Space": "sRGB",
                  "Green Component": 0.7379999999999999,
                  "Red Component": 0.63
                }
              },
              "layout advanced configuration dictionary value": {
                "algorithm": 0,
                "font": "MonaspaceArgonVar-Medium 12"
              }
            }
          },
          {
            "class": "iTermStatusBarMemoryUtilizationComponent",
            "configuration": {
              "knobs": {
                "base: compression resistance": 1,
                "base: priority": 5,
                "shared text color": {
                  "Alpha Component": 1,
                  "Blue Component": 0.9,
                  "Color Space": "sRGB",
                  "Green Component": 0.63,
                  "Red Component": 0.8460000000000002
                }
              },
              "layout advanced configuration dictionary value": {
                "algorithm": 0,
                "font": "MonaspaceArgonVar-Medium 12"
              }
            }
          }
        ]
      },
      "Sync Title": false,
      "Tags": [
        "Dynamic"
      ],
      "Terminal Type": "xterm-256color",
      "Thin Strokes": 0,
      "Transparency": 0,
      "Triggers": [
        {
          "action": "SetHostnameTrigger",
          "parameter": "\\1@\\2",
          "partial": true,
          "regex": "\\[(.+)@([^\\s\\]]+).*\\]"
        },
        {
          "action": "SetHostnameTrigger",
          "parameter": "@cvs-lab-conductor",
          "partial": true,
          "regex": "Identity added: /home/t128/[.]ssh/jump_key"
        }
      ],
      "Unicode Version": 9,
      "Unlimited Scrollback": true,
      "Use Bold Font": true,
      "Use Bright Bold": false,
      "Use Bright Bold (Dark)": false,
      "Use Bright Bold (Light)": false,
      "Use Cursor Guide (Dark)": false,
      "Use Cursor Guide (Light)": false,
      "Use Italic Font": true,
      "Use Non-ASCII Font": true,
      "Use Selected Text Color (Dark)": true,
      "Use Selected Text Color (Light)": true,
      "Use Separate Colors for Light and Dark Mode": true,
      "Use Tab Color (Dark)": false,
      "Use Tab Color (Light)": false,
      "Use Underline Color (Dark)": false,
      "Use Underline Color (Light)": false,
      "Vertical Spacing": 1,
      "Visual Bell": true,
      "Window Type": 0,
      "Working Directory": "~/Documents"
    }
  ]
}
